xia_engine_pinecone/__init__.py
xia_engine_pinecone/engine.cpython-311-darwin.so
xia_engine_pinecone-0.0.5.dist-info/LICENSE.txt
xia_engine_pinecone-0.0.5.dist-info/METADATA
xia_engine_pinecone-0.0.5.dist-info/WHEEL
xia_engine_pinecone-0.0.5.dist-info/top_level.txt
xia_engine_pinecone-0.0.5.dist-info/RECORD
