Metadata-Version: 2.1
Name: xia-engine-pinecone
Version: 0.0.5
Summary: UNKNOWN
Home-page: https://develop.x-i-a.com/docs/xia-engine-pinecone/0.0.5/index.html
Author: X-I-A
Author-email: admin@x-i-a.com
License: UNKNOWN
Platform: UNKNOWN
Requires-Python: >=3.9
License-File: LICENSE.txt
Requires-Dist: pinecone-client
Requires-Dist: xia-fields
Requires-Dist: xia-engine
